promptguru/__init__.py
promptguru/engine.py
promptguru/templates/bert.yaml
promptguru/templates/flan_t5.yaml
promptguru/templates/llama.yaml
promptguru/templates/mistral.yaml
promptguru-0.1.0.dist-info/METADATA
promptguru-0.1.0.dist-info/WHEEL
promptguru-0.1.0.dist-info/top_level.txt
promptguru-0.1.0.dist-info/RECORD
