Metadata-Version: 2.4
Name: promptguru
Version: 0.1.0
Summary: Modular prompt engineering library
Author-email: Naga Adithya Kaushik <adithyakaushikch@gmail.com>
License: Apache-2.0
Project-URL: Homepage, https://huggingface.co/spaces/GenAIDevTOProd/PromptGuru
Keywords: prompts,nlp,llm,huggingface,templates
Requires-Python: >=3.8
Requires-Dist: PyYAML>=6.0
